jinja_markdown2/__init__.py
jinja_markdown2/markdown_extension.py
jinja_markdown2/py.typed
jinja_markdown2-0.4.0.dist-info/LICENSE
jinja_markdown2-0.4.0.dist-info/METADATA
jinja_markdown2-0.4.0.dist-info/WHEEL
jinja_markdown2-0.4.0.dist-info/RECORD
