Metadata-Version: 2.1
Name: jinja-markdown2
Version: 0.4.0
Summary: A Jinja2 extension for rendering Markdown with markdown2.
Home-page: https://github.com/mkbabb/jinja-markdown2
License: MIT
Keywords: jinja2,markdown2
Author: Mike Babb
Author-email: mike7400@gmail.com
Requires-Python: >=3.10,<4.0
Classifier: License :: OSI Approved :: MIT License
Classifier: Programming Language :: Python :: 3
Classifier: Programming Language :: Python :: 3.10
Classifier: Programming Language :: Python :: 3.11
Classifier: Programming Language :: Python :: 3.12
Requires-Dist: jinja2 (>=3.1.4,<4.0.0)
Requires-Dist: markdown2 (>=2.4.13,<3.0.0)
Project-URL: Repository, https://github.com/mkbabb/jinja-markdown2
